FlagWaver/FlagWaver.py
FlagWaver/__init__.py
FlagWaver-0.0.57.dist-info/LICENSE
FlagWaver-0.0.57.dist-info/METADATA
FlagWaver-0.0.57.dist-info/WHEEL
FlagWaver-0.0.57.dist-info/top_level.txt
FlagWaver-0.0.57.dist-info/RECORD
